gaiadr3/__init__.py
gaiadr3/core.py
gaiadr3/phot_spec.py
gaiadr3/tap.py
gaiadr3/utils.py
gaiadr3-0.0.2.dist-info/LICENSE.txt
gaiadr3-0.0.2.dist-info/METADATA
gaiadr3-0.0.2.dist-info/WHEEL
gaiadr3-0.0.2.dist-info/top_level.txt
gaiadr3-0.0.2.dist-info/RECORD
