Metadata-Version: 2.1
Name: gaiadr3
Version: 0.0.2
Summary: Retrieve data and analysis package for Gaia Data Release 3
Home-page: https://github.com/behrouzz/gaiadr3
Author: Behrouz Safari
Author-email: behrouz.safari@gmail.com
License: MIT
Classifier: Programming Language :: Python :: 3
Classifier: License :: OSI Approved :: MIT License
Classifier: Operating System :: OS Independent
Requires-Python: >=3.6
License-File: LICENSE.txt
Requires-Dist: numpy
Requires-Dist: pandas
